{
    "Game Objects": [
        {
            "name": "Area Light",
            "tag": "Untagged",
            "layer": "Default",
            "Active": true,
            "UID": 2072640645,
            "ParentUID": 8413079,
            "PrefabReference": 0,
            "PrefabID": 0,
            "DontDestroy": false,
            "Static": false,
            "Position": [
                -8.4014863967895508,
                -7.796600341796875,
                -30.328201293945313
            ],
            "Rotation": [
                0,
                0,
                0,
                1
            ],
            "Scale": [
                1,
                1,
                1
            ],
            "Components": [
                {
                    "Type": 1,
                    "Active": true
                },
                {
                    "Type": 27,
                    "Active": true,
                    "lightColor": [
                        0.99215686321258545,
                        0.729411780834198,
                        0.19607843458652496
                    ],
                    "ambientLightColor": [
                        1,
                        0,
                        0
                    ],
                    "lightIntensity": 6,
                    "specularValue": 1,
                    "fadeDistance": 20,
                    "maxDistance": 150,
                    "calculateShadows": true
                }
            ]
        }
    ]
}